cosmo_file/__init__.py
cosmo_file/__main__.py
cosmo_file/_version.py
cosmo_file/data/COPYING
cosmo_file/data/file.com
cosmo_file/data/platform
cosmo_file-5.46.3.dist-info/licenses/LICENSE
cosmo_file-5.46.3.dist-info/METADATA
cosmo_file-5.46.3.dist-info/WHEEL
cosmo_file-5.46.3.dist-info/entry_points.txt
cosmo_file-5.46.3.dist-info/top_level.txt
cosmo_file-5.46.3.dist-info/RECORD
