Metadata-Version: 2.4
Name: cosmo-file
Version: 5.46.3
Summary: Cosmopolitan builds of file(1), distributed as a Python package
Author: cosmo-file contributors
License: MIT License
Project-URL: Homepage, https://github.com/bjia56/cosmo-file
Project-URL: Repository, https://github.com/bjia56/cosmo-file
Project-URL: Issues, https://github.com/bjia56/cosmo-file/issues
Classifier: Development Status :: 4 - Beta
Classifier: Intended Audience :: Developers
Classifier: License :: OSI Approved :: MIT License
Classifier: Operating System :: OS Independent
Classifier: Programming Language :: Python :: 3
Classifier: Programming Language :: Python :: 3.8
Classifier: Programming Language :: Python :: 3.9
Classifier: Programming Language :: Python :: 3.10
Classifier: Programming Language :: Python :: 3.11
Classifier: Programming Language :: Python :: 3.12
Classifier: Topic :: Software Development :: Libraries :: Python Modules
Classifier: Topic :: System :: Filesystems
Requires-Python: >=3.8
License-File: LICENSE
Dynamic: license-file
